recc_database/__init__.py
recc_database/chrono/__init__.py
recc_database/chrono/datetime.py
recc_database/database/__init__.py
recc_database/database/pg_common.py
recc_database/database/pg_db.py
recc_database/database/query_builder.py
recc_database/database/query_utils.py
recc_database/database/mixin/__init__.py
recc_database/database/mixin/_pg_base.py
recc_database/database/mixin/pg_group.py
recc_database/database/mixin/pg_group_member.py
recc_database/database/mixin/pg_info.py
recc_database/database/mixin/pg_permission.py
recc_database/database/mixin/pg_pip.py
recc_database/database/mixin/pg_project.py
recc_database/database/mixin/pg_project_member.py
recc_database/database/mixin/pg_role.py
recc_database/database/mixin/pg_role_permission.py
recc_database/database/mixin/pg_task.py
recc_database/database/mixin/pg_user.py
recc_database/database/mixin/pg_user_info.py
recc_database/database/query/__init__.py
recc_database/database/query/group.py
recc_database/database/query/group_member.py
recc_database/database/query/info.py
recc_database/database/query/permission.py
recc_database/database/query/pip.py
recc_database/database/query/project.py
recc_database/database/query/project_member.py
recc_database/database/query/role.py
recc_database/database/query/role_permission.py
recc_database/database/query/task.py
recc_database/database/query/user.py
recc_database/database/query/user_info.py
recc_database/database/query/create/__init__.py
recc_database/database/query/create/indices.py
recc_database/database/query/create/tables.py
recc_database/database/query/create/timescale.py
recc_database/database/query/create/views.py
recc_database/database/query/create/functions/__init__.py
recc_database/database/query/create/functions/appropriate_permission.py
recc_database/packet/__init__.py
recc_database/packet/group.py
recc_database/packet/group_join_member.py
recc_database/packet/group_member.py
recc_database/packet/info.py
recc_database/packet/member.py
recc_database-2.1.0.dist-info/LICENSE
recc_database-2.1.0.dist-info/METADATA
recc_database-2.1.0.dist-info/WHEEL
recc_database-2.1.0.dist-info/top_level.txt
recc_database-2.1.0.dist-info/RECORD
